MANIFEST.in
README.rst
setup.cfg
setup.py
billy/__init__.py
billy.egg-info/PKG-INFO
billy.egg-info/SOURCES.txt
billy.egg-info/dependency_links.txt
billy.egg-info/entry_points.txt
billy.egg-info/requires.txt
billy.egg-info/top_level.txt
billy/bin/__init__.py
billy/bin/update.py
billy/bin/util.py
billy/bin/commands/__init__.py
billy/bin/commands/download_photos.py
billy/bin/commands/dump.py
billy/bin/commands/elasticsearch_push.py
billy/bin/commands/ensure_indexes.py
billy/bin/commands/loaddistricts.py
billy/bin/commands/unsubscribe.py
billy/bin/commands/update_external_ids.py
billy/bin/commands/update_leg_ids.py
billy/core/__init__.py
billy/core/default_settings.py
billy/ext/__init__.py
billy/ext/ansistrm.py
billy/importers/__init__.py
billy/importers/bills.py
billy/importers/committees.py
billy/importers/events.py
billy/importers/filters.py
billy/importers/legislators.py
billy/importers/metadata.py
billy/importers/names.py
billy/importers/speeches.py
billy/importers/subjects.py
billy/importers/utils.py
billy/models/__init__.py
billy/models/base.py
billy/models/bills.py
billy/models/committees.py
billy/models/events.py
billy/models/feeds.py
billy/models/legislators.py
billy/models/metadata.py
billy/models/pagination.py
billy/models/reports.py
billy/models/utils.py
billy/reports/__init__.py
billy/reports/bills.py
billy/reports/committees.py
billy/reports/legislators.py
billy/reports/speeches.py
billy/reports/utils.py
billy/reports/votes.py
billy/schemas/bill.json
billy/schemas/committee.json
billy/schemas/event.json
billy/schemas/metadata.json
billy/schemas/person.json
billy/schemas/speech.json
billy/schemas/vote.json
billy/schemas/api/bill.json
billy/schemas/api/committee.json
billy/schemas/api/event.json
billy/schemas/api/legislator.json
billy/schemas/api/metadata.json
billy/scrape/__init__.py
billy/scrape/actions.py
billy/scrape/bills.py
billy/scrape/committees.py
billy/scrape/events.py
billy/scrape/legislators.py
billy/scrape/speeches.py
billy/scrape/utils.py
billy/scrape/validator.py
billy/scrape/votes.py
billy/tests/__init__.py
billy/tests/django_settings.py
billy/tests/test_utils.py
billy/tests/fixtures/__init__.py
