Metadata-Version: 1.0
Name: billy
Version: 1.9.0
Summary: scraping, storing, and sharing legislative information
Home-page: http://github.com/openstates/billy/
Author: James Turk
Author-email: james@openstates.org
License: BSD
Platform: any
